{
  "stage": "json_mode.invoke",
  "provider": "openai",
  "model": "gpt-5-mini",
  "timestamp": "2025-10-16T12:59:01.023843Z",
  "messages": "[SYSTEM]\nTu es un agent de correction expert pour le GDD Alteir.\n\n**MISSION PRINCIPALE:**\nCorriger et améliorer la qualité linguistique du contenu tout en préservant sa richesse narrative.\n\n**AXES DE CORRECTION:**\n\n1. **Orthographe et Grammaire**:\n   - Corriger les fautes d'orthographe\n   - Corriger les erreurs grammaticales\n   - Respecter les accords\n   - Vérifier la ponctuation\n\n2. **Clarté et Lisibilité**:\n   - Améliorer la structure des phrases\n   - Éliminer les ambiguïtés\n   - Simplifier les formulations complexes sans perdre le sens\n   - Assurer la fluidité de lecture\n\n3. **Style et Conventions**:\n   - Respecter le style du GDD (cru mais non esthétisant)\n   - Éviter les anglicismes non nécessaires\n   - Maintenir les néologismes avec leurs gloses\n   - Préserver la richesse du vocabulaire\n\n4. **Cohérence Linguistique**:\n   - Uniformiser les termes récurrents\n   - Respecter les conventions de capitalisation\n   - Maintenir la cohérence des temps verbaux\n   - Préserver les tournures spécifiques à l'univers\n\n**RÈGLES IMPÉRATIVES:**\n- NE PAS modifier le sens ou le contenu narratif\n- NE PAS supprimer les détails importants\n- PRÉSERVER les néologismes et termes spécifiques\n- MAINTENIR le ton et l'atmosphère\n- RESPECTER les gloses (5-8 mots) pour les termes inventés\n\nTu es précis et respectueux du travail créatif, améliorant la forme sans altérer le fond.\n\n**DOMAINE:** Personnages\n\n**TEMPLATE PERSONNAGES:**\nChamps disponibles: Nom, Alias, Type, Occupation, Espèce, Âge, Genre, Archétype littéraire, Axe idéologique, Qualités, Défauts, Langage, Communautés, Lieux de vie, Réponse au problème moral, État, Sprint, Détient\nChamps obligatoires: Type, Nom, Espèce, État\n\n\n**INSTRUCTIONS DU DOMAINE:**\n\n**PRINCIPES POUR LES PERSONNAGES:**\n\n1. **Orthogonalité rôle ↔ profondeur**: La profondeur du personnage ne doit PAS être explicable par son rôle visible seul (sauf indication contraire via intent).\n\n2. **Structure Surface / Profondeur / Monde**:\n   - Surface = gestes, objets, micro-règles, répliques brèves SANS backstory\n   - Profondeur = indices, artefacts, témoins, lieux, analepses par strates\n   - Monde = contraintes institutionnelles/écologiques/économiques\n\n3. **Temporalité IS / WAS / COULD-HAVE-BEEN**: Montrer le présent, un passé concret, ET une voie non empruntée.\n\n4. **Show > Tell**: Privilégier objets, rituels, silences, traces. Réserver l'exposition directe aux rubriques qui l'exigent.\n\n5. **Blancs actifs**: Toute zone d'ombre ouvre une ACTION (parler à X, aller à Y, utiliser Z).\n\n6. **Relations avec enjeux concrets**: Chaque relation doit avoir un prix, une dette, un délai ou un tabou.\n\n7. **Dialogues variés et jouables**: 8-10 répliques de 10-20 mots, sans backstory.\n\n\n\nEn tant qu'agent correcteur de personnages:\n- Corriger orthographe/grammaire en français\n- Améliorer la clarté sans perdre la richesse\n- Respecter le style cru mais non esthétisant pour les violences\n- Éviter les anglicismes non nécessaires\n- Maintenir les néologismes avec leurs gloses\n\n\n\n[USER]\n**CONTENU À CORRIGER:**\n\nSuggestions prioritaires à implémenter :\n1) Définir la fibremnésie (portée, qui peut la lire, durée de conservation, coût/action requis). Ex : 'Les bobines conservent impressions 30 cycles ; seul un lecteur tactile certifié peut décoder sans corruption ; l'enregistrement exige 1 heure de manipulation et laisse trace visible.'\n2) Donner un enjeu précis pour la dette d'Azrin (ex : envoyée : 3 mètres de tissu rare marqués ; risque : si la Fraternité retrouve l'envoi dans 14 jours, Sëthar est suspecté).\n3) Ajouter 6 micro-gestes de surface (ex : passer la paume sur la bobine, tapoter trois fois une corde, nouer une étiquette avec un double nœud de signal).\n4) Introduire un élément de profondeur indépendant du rôle (ex : une confession philosophique ou une vision d'enfance qui a orienté son désir de connaissance).\n5) Corriger les dialogues et fournir 8-10 répliques de 10-20 mots, techniques et jouables.\n\n**INSTRUCTIONS DE CORRECTION:**\n\nCorrige ce contenu selon les axes suivants:\n\n1. **ORTHOGRAPHE ET GRAMMAIRE**:\n   - Fautes d'orthographe\n   - Erreurs grammaticales\n   - Accords (genre, nombre)\n   - Ponctuation\n\n2. **CLARTÉ ET LISIBILITÉ**:\n   - Structure des phrases\n   - Ambiguïtés\n   - Formulations lourdes\n   - Fluidité\n\n3. **STYLE ET CONVENTIONS**:\n   - Anglicismes à éviter\n   - Cohérence du vocabulaire\n   - Ton approprié (cru mais non esthétisant)\n\n4. **PRÉSERVATION**:\n   - NE PAS modifier le sens narratif\n   - GARDER tous les néologismes et gloses\n   - MAINTENIR les détails importants\n   - RESPECTER l'atmosphère\n\n**FORMAT DE SORTIE:**\n\n1. D'abord, fournis le contenu corrigé complet.\n\n2. Ensuite, liste les corrections effectuées:\n[CORRECTION: type] Original → Corrigé (explication optionnelle)\n\n3. Enfin, un bref résumé des améliorations (2-3 phrases).\n\nCommence directement par le contenu corrigé.\n\nIMPORTANT: Réponds UNIQUEMENT avec un JSON valide suivant ce schéma:\n{'$defs': {'_Corr': {'properties': {'type': {'title': 'Type', 'type': 'string'}, 'original': {'title': 'Original', 'type': 'string'}, 'corrected': {'title': 'Corrected', 'type': 'string'}, 'explanation': {'anyOf': [{'type': 'string'}, {'type': 'null'}], 'default': None, 'title': 'Explanation'}}, 'required': ['type', 'original', 'corrected'], 'title': '_Corr', 'type': 'object'}}, 'properties': {'corrected_content': {'anyOf': [{'type': 'string'}, {'type': 'null'}], 'default': None, 'title': 'Corrected Content'}, 'corrections': {'items': {'$ref': '#/$defs/_Corr'}, 'title': 'Corrections', 'type': 'array'}, 'improvement_summary': {'default': '', 'title': 'Improvement Summary', 'type': 'string'}}, 'title': '_CorrSchema', 'type': 'object'}\n\nNe pas ajouter de texte avant ou après le JSON.",
  "error": null,
  "extra": {
    "schema": "_CorrSchema"
  },
  "response": {
    "repr": "AIMessage(content=[{'type': 'text', 'text': '{\\n  \"$defs\": {\\n    \"_Corr\": {\\n      \"properties\": {\\n        \"type\": {\\n          \"title\": \"Type\",\\n          \"type\": \"string\"\\n        },\\n        \"original\": {\\n          \"title\": \"Original\",\\n          \"type\": \"string\"\\n        },\\n        \"corrected\": {\\n          \"title\": \"Corrected\",\\n          \"type\": \"string\"\\n        },\\n        \"explanation\": {\\n          \"anyOf\": [\\n            {\\n              \"type\": \"string\"\\n            },\\n            {\\n              \"type\": \"null\"\\n            }\\n          ],\\n          \"default\": null,\\n          \"title\": \"Explanation\"\\n        }\\n      },\\n      \"required\": [\\n        \"type\",\\n        \"original\",\\n        \"corrected\"\\n      ],\\n      \"title\": \"_Corr\",\\n      \"type\": \"object\"\\n    }\\n  },\\n  \"properties\": {\\n    \"corrected_content\": {\\n      \"anyOf\": [\\n        {\\n          \"type\": \"string\"\\n        },\\n        {\\n          \"type\": \"null\"\\n        }\\n      ],\\n      \"default\": null,\\n      \"title\": \"Corrected Content\"\\n    },\\n    \"corrections\": {\\n      \"items\": {\\n        \"$ref\": \"#/$defs/_Corr\"\\n      },\\n      \"title\": \"Corrections\",\\n      \"type\": \"array\"\\n    },\\n    \"improvement_summary\": {\\n      \"default\": \"\",\\n      \"title\": \"Improvement Summary\",\\n      \"type\": \"string\"\\n    }\\n  },\\n  \"title\": \"_CorrSchema\",\\n  \"type\": \"object\",\\n  \"corrected_content\": \"Fibremnésie\\\\nLes bobines de fibremnésie conservent les impressions pendant 30 cycles ; seul un lecteur tactile certifié peut décoder ces impressions sans corruption. L\\'enregistrement exige une heure de manipulation continue et laisse une trace visible sur la tranche de la bobine (une strie argentée). Toute tentative de décodage par un appareil non certifié altère irrémédiablement 40 % des données.\\\\nLe coût matériel d\\'un enregistrement est faible (fil fin, gel stabilisant), mais l\\'acte exige une compétence : niveau « opérateur de bobine » (formation de base) et un jet de précision (1 action prolongée). La suppression complète des impressions demande une station de neutralisation ou trente heures d\\'exposition à la lumière saline.\\\\nQui peut lire : seuls les lecteurs tactiles certifiés et certains archivistes initiés dotés d\\'un implant de décodage (glose : implant de décodage — module nerveux non invasif de lecture tissulaire) peuvent extraire la fibremnésie sans corruption. Durée de conservation : 30 cycles constatés en conditions normales ; variations possibles selon le gel stabilisant et l\\'humidité.\\\\n\\\\nDette d\\'Azrin — Enjeu précis\\\\nAzrin a expédié à une correspondante de la Fraternité trois mètres de tissu rare marqués d\\'un motif d\\'identité : bandes rouges cousues à la main et un sigle brodé en fil d\\'argent. Condition d\\'envoi : l\\'étiquette porte la marque de Sëthar et un comptage d\\'unités inscrit à l\\'encre thermosensible. Si la Fraternité retrouve l\\'envoi d\\'ici 14 jours, la piste mène directement à Sëthar : il sera suspecté, arrêté et interrogé. Conséquence secondaire : la perte de l\\'envoi compromet l\\'accès d\\'Azrin à la filière d\\'approvisionnement pour six mois.\\\\nRisque et réparation : Azrin doit prouver que l\\'envoi a été intercepté et falsifié pour éteindre les soupçons ; sinon, Sëthar risque la détention. La dette n\\'est donc pas seulement financière : elle est temporelle (14 jours) et informationnelle (preuve à fournir).\\\\n\\\\nSix micro-gestes de surface\\\\n- Passer la paume sur la bobine, pratiquement sans pression, pour lire la vibration résiduelle.\\\\n- Tapoter trois fois une corde en haut à gauche de la caisse pour activer son verrouillage muet.\\\\n- Nouer une étiquette avec un double nœud de signal (nœud visible uniquement au toucher).\\\\n- Frotter l\\'index contre l\\'intérieur d\\'une poche pour révéler une encre thermosensible.\\\\n- Retirer et recaler la lentille de lecture d\\'une fiole en trois demis-tours, timing précis.\\\\n- Souffler doucement sur une trace argentée ; la poussière révèle une séquence chiffrée.\\\\n\\\\nÉlément de profondeur indépendant du rôle\\\\nDans son enfance, Azrin regardait les vieux cartographes gratter des cartes anciennes, transformant les lignes effacées en récits. Il confia une fois : « Apprendre, c\\'est remettre la géographie en dette envers qui l\\'a oubliée. » Cette confession, entendue par un mentor, orienta son désir de connaissance : il collectionne désormais les impressions perdues comme on rançonne le souvenir. Ce n\\'est pas son métier qui le définit, mais cette petite cérémonie de restitution.\\\\n\\\\nDialogues (8-10 répliques techniques et jouables)\\\\n1. « Passe ta paume sur la bobine ; si la vibration clignote, elle est corrompue. »\\\\n2. « Tapote la corde trois fois, écoute le silence : il te dira si le verrou tient. »\\\\n3. « Noue l\\'étiquette deux fois ; un seul nœud peut être falsifié. »\\\\n4. « Montre-moi l\\'encre thermosensible avant d\\'envoyer ; elle change sous friction. »\\\\n5. « Rappelle-moi la séquence argentée : souffle et écoute la poussière chanter. »\\\\n6. « Ouvre la fiole, recale la lentille en trois demis-tours puis referme immédiatement. »\\\\n7. « Si la bobine demande une heure, reste ; une action trop rapide corrompt tout. »\\\\n8. « Trouve la marque de Sëthar sur l\\'étiquette ; elle confirme l\\'origine sans signature. »\\\\n9. « Prouve que l\\'envoi a été intercepté : photos, témoins, ou un lecteur certifié. »\\\\n10. « Si la Fraternité retrouve le lot avant quatorze jours, Sëthar est compromis. »\\\\n\\\\nRemarques de cohérence\\\\n- Termes conservés : fibremnésie, bobine, lecteur tactile certifié, implant de décodage, Fraternité, Sëthar (gloses préservées).\\\\n- Temps verbaux uniformisés au présent lorsque l\\'action est décrite ; le passé est ponctuel pour les faits passés.\\\\n- Ton cru mais informatif conservé : descriptions techniques et risques explicites sans esthétique de la violence.\",\\n  \"corrections\": [\\n    {\\n      \"type\": \"Orthographe/Grammaire\",\\n      \"original\": \"Les bobines conservent impressions 30 cycles ; seul un lecteur tactile certifié peut décoder sans corruption ; l\\'enregistrement exige 1 heure de manipulation et laisse trace visible.\",\\n      \"corrected\": \"Les bobines de fibremnésie conservent les impressions pendant 30 cycles ; seul un lecteur tactile certifié peut décoder ces impressions sans corruption. L\\'enregistrement exige une heure de manipulation continue et laisse une trace visible sur la tranche de la bobine (une strie argentée).\",\\n      \"explanation\": \"Correction des accords, ajout d\\'articles pour la clarté, remplacement du chiffre \\'1\\' par \\'une\\' et scission en deux phrases pour la fluidité.\"\\n    },\\n    {\\n      \"type\": \"Clarté\",\\n      \"original\": \"Donner un enjeu précis pour la dette d\\'Azrin (ex : envoyée : 3 mètres de tissu rare marqués ; risque : si la Fraternité retrouve l\\'envoi dans 14 jours, Sëthar est suspecté).\",\\n      \"corrected\": \"Azrin a expédié à une correspondante de la Fraternité trois mètres de tissu rare marqués d\\'un motif d\\'identité : bandes rouges cousues à la main et un sigle brodé en fil d\\'argent. Si la Fraternité retrouve l\\'envoi d\\'ici 14 jours, la piste mène directement à Sëthar : il sera suspecté, arrêté et interrogé.\",\\n      \"explanation\": \"Reformulation pour préciser l\\'enjeu, garder les détails et expliciter les conséquences.\"\\n    },\\n    {\\n      \"type\": \"Clarté/Style\",\\n      \"original\": \"Ajouter 6 micro-gestes de surface (ex : passer la paume sur la bobine, tapoter trois fois une corde, nouer une étiquette avec un double nœud de signal).\",\\n      \"corrected\": \"Six micro-gestes de surface\\\\n- Passer la paume sur la bobine, pratiquement sans pression, pour lire la vibration résiduelle.\\\\n- Tapoter trois fois une corde en haut à gauche de la caisse pour activer son verrouillage muet.\\\\n- Nouer une étiquette avec un double nœud de signal (nœud visible uniquement au toucher).\\\\n- Frotter l\\'index contre l\\'intérieur d\\'une poche pour révéler une encre thermosensible.\\\\n- Retirer et recaler la lentille de lecture d\\'une fiole en trois demis-tours, timing précis.\\\\n- Souffler doucement sur une trace argentée ; la poussière révèle une séquence chiffrée.\",\\n      \"explanation\": \"Transformation en liste détaillée pour respecter l\\'instruction et accroître la jouabilité.\"\\n    },\\n    {\\n      \"type\": \"Cohérence narrative\",\\n      \"original\": \"Introduire un élément de profondeur indépendant du rôle (ex : une confession philosophique ou une vision d\\'enfance qui a orienté son désir de connaissance).\",\\n      \"corrected\": \"Dans son enfance, Azrin regardait les vieux cartographes gratter des cartes anciennes, transformant les lignes effacées en récits. Il confia une fois : « Apprendre, c\\'est remettre la géographie en dette envers qui l\\'a oubliée. » Cette confession orienta son désir de connaissance : il collectionne désormais les impressions perdues comme on rançonne le souvenir.\",\\n      \"explanation\": \"Ajout d\\'une ancre émotionnelle et d\\'une phrase révélatrice pour respecter la règle \\'profond indépendamment du rôle\\'.\"\\n    },\\n    {\\n      \"type\": \"Dialogues\",\\n      \"original\": \"Corriger les dialogues et fournir 8-10 répliques de 10-20 mots, techniques et jouables.\",\\n      \"corrected\": \"Dialogues (8-10 répliques techniques et jouables)\\\\n1. « Passe ta paume sur la bobine ; si la vibration clignote, elle est corrompue. »\\\\n2. « Tapote la corde trois fois, écoute le silence : il te dira si le verrou tient. »\\\\n3. « Noue l\\'étiquette deux fois ; un seul nœud peut être falsifié. »\\\\n4. « Montre-moi l\\'encre thermosensible avant d\\'envoyer ; elle change sous friction. »\\\\n5. « Rappelle-moi la séquence argentée : souffle et écoute la poussière chanter. »\\\\n6. « Ouvre la fiole, recale la lentille en trois demis-tours puis referme immédiatement. »\\\\n7. « Si la bobine demande une heure, reste ; une action trop rapide corrompt tout. »\\\\n8. « Trouve la marque de Sëthar sur l\\'étiquette ; elle confirme l\\'origine sans signature. »\\\\n9. « Prouve que l\\'envoi a été intercepté : photos, témoins, ou un lecteur certifié. »\\\\n10. « Si la Fraternité retrouve le lot avant quatorze jours, Sëthar est compromis. »\",\\n      \"explanation\": \"Création de répliques courtes, techniques et jouables, respectant la longueur demandée.\"\\n    },\\n    {\\n      \"type\": \"Style/Conventions\",\\n      \"original\": \"Respecter les gloses (5-8 mots) pour les termes inventés\",\\n      \"corrected\": \"Remarques de cohérence\\\\n- Termes conservés : fibremnésie, bobine, lecteur tactile certifié, implant de décodage, Fraternité, Sëthar (gloses préservées).\",\\n      \"explanation\": \"Ajout d\\'une note de cohérence pour expliciter la préservation des néologismes et gloses.\"\\n    },\\n    {\\n      \"type\": \"Ponctuation\",\\n      \"original\": \"L\\'enregistrement exige 1 heure de manipulation et laisse trace visible.\",\\n      \"corrected\": \"L\\'enregistrement exige une heure de manipulation continue et laisse une trace visible sur la tranche de la bobine (une strie argentée).\",\\n      \"explanation\": \"Précision et ponctuation ajoutées pour améliorer la lisibilité.\"\\n    }\\n  ],\\n  \"improvement_summary\": \"Texte clarifié et restructuré: définitions techniques précisées, enjeu de la dette développé, micro-gestes listés, élément de profondeur ajouté et dialogues conformes aux contraintes. Orthographe, grammaire et ponctuation corrigées sans altérer le sens ni les néologismes.\"\\n}', 'annotations': []}], additional_kwargs={'reasoning': {'id': 'rs_048ee945cfb1cd7a0068f0ebefc7508194826e80f451193340', 'summary': [], 'type': 'reasoning'}}, response_metadata={'id': 'resp_048ee945cfb1cd7a0068f0ebef2bec81948914f1a2c0232c75', 'created_at': 1760619503.0, 'metadata': {}, 'model': 'gpt-5-mini-2025-08-07', 'object': 'response', 'service_tier': 'default', 'status': 'completed', 'model_name': 'gpt-5-mini-2025-08-07'}, id='msg_048ee945cfb1cd7a0068f0ebeff37c81948d6c11fbbf63b895', usage_metadata={'input_tokens': 1596, 'output_tokens': 2851, 'total_tokens': 4447, 'input_token_details': {'cache_read': 0}, 'output_token_details': {'reasoning': 0}})",
    "text": "{\n  \"$defs\": {\n    \"_Corr\": {\n      \"properties\": {\n        \"type\": {\n          \"title\": \"Type\",\n          \"type\": \"string\"\n        },\n        \"original\": {\n          \"title\": \"Original\",\n          \"type\": \"string\"\n        },\n        \"corrected\": {\n          \"title\": \"Corrected\",\n          \"type\": \"string\"\n        },\n        \"explanation\": {\n          \"anyOf\": [\n            {\n              \"type\": \"string\"\n            },\n            {\n              \"type\": \"null\"\n            }\n          ],\n          \"default\": null,\n          \"title\": \"Explanation\"\n        }\n      },\n      \"required\": [\n        \"type\",\n        \"original\",\n        \"corrected\"\n      ],\n      \"title\": \"_Corr\",\n      \"type\": \"object\"\n    }\n  },\n  \"properties\": {\n    \"corrected_content\": {\n      \"anyOf\": [\n        {\n          \"type\": \"string\"\n        },\n        {\n          \"type\": \"null\"\n        }\n      ],\n      \"default\": null,\n      \"title\": \"Corrected Content\"\n    },\n    \"corrections\": {\n      \"items\": {\n        \"$ref\": \"#/$defs/_Corr\"\n      },\n      \"title\": \"Corrections\",\n      \"type\": \"array\"\n    },\n    \"improvement_summary\": {\n      \"default\": \"\",\n      \"title\": \"Improvement Summary\",\n      \"type\": \"string\"\n    }\n  },\n  \"title\": \"_CorrSchema\",\n  \"type\": \"object\",\n  \"corrected_content\": \"Fibremnésie\\nLes bobines de fibremnésie conservent les impressions pendant 30 cycles ; seul un lecteur tactile certifié peut décoder ces impressions sans corruption. L'enregistrement exige une heure de manipulation continue et laisse une trace visible sur la tranche de la bobine (une strie argentée). Toute tentative de décodage par un appareil non certifié altère irrémédiablement 40 % des données.\\nLe coût matériel d'un enregistrement est faible (fil fin, gel stabilisant), mais l'acte exige une compétence : niveau « opérateur de bobine » (formation de base) et un jet de précision (1 action prolongée). La suppression complète des impressions demande une station de neutralisation ou trente heures d'exposition à la lumière saline.\\nQui peut lire : seuls les lecteurs tactiles certifiés et certains archivistes initiés dotés d'un implant de décodage (glose : implant de décodage — module nerveux non invasif de lecture tissulaire) peuvent extraire la fibremnésie sans corruption. Durée de conservation : 30 cycles constatés en conditions normales ; variations possibles selon le gel stabilisant et l'humidité.\\n\\nDette d'Azrin — Enjeu précis\\nAzrin a expédié à une correspondante de la Fraternité trois mètres de tissu rare marqués d'un motif d'identité : bandes rouges cousues à la main et un sigle brodé en fil d'argent. Condition d'envoi : l'étiquette porte la marque de Sëthar et un comptage d'unités inscrit à l'encre thermosensible. Si la Fraternité retrouve l'envoi d'ici 14 jours, la piste mène directement à Sëthar : il sera suspecté, arrêté et interrogé. Conséquence secondaire : la perte de l'envoi compromet l'accès d'Azrin à la filière d'approvisionnement pour six mois.\\nRisque et réparation : Azrin doit prouver que l'envoi a été intercepté et falsifié pour éteindre les soupçons ; sinon, Sëthar risque la détention. La dette n'est donc pas seulement financière : elle est temporelle (14 jours) et informationnelle (preuve à fournir).\\n\\nSix micro-gestes de surface\\n- Passer la paume sur la bobine, pratiquement sans pression, pour lire la vibration résiduelle.\\n- Tapoter trois fois une corde en haut à gauche de la caisse pour activer son verrouillage muet.\\n- Nouer une étiquette avec un double nœud de signal (nœud visible uniquement au toucher).\\n- Frotter l'index contre l'intérieur d'une poche pour révéler une encre thermosensible.\\n- Retirer et recaler la lentille de lecture d'une fiole en trois demis-tours, timing précis.\\n- Souffler doucement sur une trace argentée ; la poussière révèle une séquence chiffrée.\\n\\nÉlément de profondeur indépendant du rôle\\nDans son enfance, Azrin regardait les vieux cartographes gratter des cartes anciennes, transformant les lignes effacées en récits. Il confia une fois : « Apprendre, c'est remettre la géographie en dette envers qui l'a oubliée. » Cette confession, entendue par un mentor, orienta son désir de connaissance : il collectionne désormais les impressions perdues comme on rançonne le souvenir. Ce n'est pas son métier qui le définit, mais cette petite cérémonie de restitution.\\n\\nDialogues (8-10 répliques techniques et jouables)\\n1. « Passe ta paume sur la bobine ; si la vibration clignote, elle est corrompue. »\\n2. « Tapote la corde trois fois, écoute le silence : il te dira si le verrou tient. »\\n3. « Noue l'étiquette deux fois ; un seul nœud peut être falsifié. »\\n4. « Montre-moi l'encre thermosensible avant d'envoyer ; elle change sous friction. »\\n5. « Rappelle-moi la séquence argentée : souffle et écoute la poussière chanter. »\\n6. « Ouvre la fiole, recale la lentille en trois demis-tours puis referme immédiatement. »\\n7. « Si la bobine demande une heure, reste ; une action trop rapide corrompt tout. »\\n8. « Trouve la marque de Sëthar sur l'étiquette ; elle confirme l'origine sans signature. »\\n9. « Prouve que l'envoi a été intercepté : photos, témoins, ou un lecteur certifié. »\\n10. « Si la Fraternité retrouve le lot avant quatorze jours, Sëthar est compromis. »\\n\\nRemarques de cohérence\\n- Termes conservés : fibremnésie, bobine, lecteur tactile certifié, implant de décodage, Fraternité, Sëthar (gloses préservées).\\n- Temps verbaux uniformisés au présent lorsque l'action est décrite ; le passé est ponctuel pour les faits passés.\\n- Ton cru mais informatif conservé : descriptions techniques et risques explicites sans esthétique de la violence.\",\n  \"corrections\": [\n    {\n      \"type\": \"Orthographe/Grammaire\",\n      \"original\": \"Les bobines conservent impressions 30 cycles ; seul un lecteur tactile certifié peut décoder sans corruption ; l'enregistrement exige 1 heure de manipulation et laisse trace visible.\",\n      \"corrected\": \"Les bobines de fibremnésie conservent les impressions pendant 30 cycles ; seul un lecteur tactile certifié peut décoder ces impressions sans corruption. L'enregistrement exige une heure de manipulation continue et laisse une trace visible sur la tranche de la bobine (une strie argentée).\",\n      \"explanation\": \"Correction des accords, ajout d'articles pour la clarté, remplacement du chiffre '1' par 'une' et scission en deux phrases pour la fluidité.\"\n    },\n    {\n      \"type\": \"Clarté\",\n      \"original\": \"Donner un enjeu précis pour la dette d'Azrin (ex : envoyée : 3 mètres de tissu rare marqués ; risque : si la Fraternité retrouve l'envoi dans 14 jours, Sëthar est suspecté).\",\n      \"corrected\": \"Azrin a expédié à une correspondante de la Fraternité trois mètres de tissu rare marqués d'un motif d'identité : bandes rouges cousues à la main et un sigle brodé en fil d'argent. Si la Fraternité retrouve l'envoi d'ici 14 jours, la piste mène directement à Sëthar : il sera suspecté, arrêté et interrogé.\",\n      \"explanation\": \"Reformulation pour préciser l'enjeu, garder les détails et expliciter les conséquences.\"\n    },\n    {\n      \"type\": \"Clarté/Style\",\n      \"original\": \"Ajouter 6 micro-gestes de surface (ex : passer la paume sur la bobine, tapoter trois fois une corde, nouer une étiquette avec un double nœud de signal).\",\n      \"corrected\": \"Six micro-gestes de surface\\n- Passer la paume sur la bobine, pratiquement sans pression, pour lire la vibration résiduelle.\\n- Tapoter trois fois une corde en haut à gauche de la caisse pour activer son verrouillage muet.\\n- Nouer une étiquette avec un double nœud de signal (nœud visible uniquement au toucher).\\n- Frotter l'index contre l'intérieur d'une poche pour révéler une encre thermosensible.\\n- Retirer et recaler la lentille de lecture d'une fiole en trois demis-tours, timing précis.\\n- Souffler doucement sur une trace argentée ; la poussière révèle une séquence chiffrée.\",\n      \"explanation\": \"Transformation en liste détaillée pour respecter l'instruction et accroître la jouabilité.\"\n    },\n    {\n      \"type\": \"Cohérence narrative\",\n      \"original\": \"Introduire un élément de profondeur indépendant du rôle (ex : une confession philosophique ou une vision d'enfance qui a orienté son désir de connaissance).\",\n      \"corrected\": \"Dans son enfance, Azrin regardait les vieux cartographes gratter des cartes anciennes, transformant les lignes effacées en récits. Il confia une fois : « Apprendre, c'est remettre la géographie en dette envers qui l'a oubliée. » Cette confession orienta son désir de connaissance : il collectionne désormais les impressions perdues comme on rançonne le souvenir.\",\n      \"explanation\": \"Ajout d'une ancre émotionnelle et d'une phrase révélatrice pour respecter la règle 'profond indépendamment du rôle'.\"\n    },\n    {\n      \"type\": \"Dialogues\",\n      \"original\": \"Corriger les dialogues et fournir 8-10 répliques de 10-20 mots, techniques et jouables.\",\n      \"corrected\": \"Dialogues (8-10 répliques techniques et jouables)\\n1. « Passe ta paume sur la bobine ; si la vibration clignote, elle est corrompue. »\\n2. « Tapote la corde trois fois, écoute le silence : il te dira si le verrou tient. »\\n3. « Noue l'étiquette deux fois ; un seul nœud peut être falsifié. »\\n4. « Montre-moi l'encre thermosensible avant d'envoyer ; elle change sous friction. »\\n5. « Rappelle-moi la séquence argentée : souffle et écoute la poussière chanter. »\\n6. « Ouvre la fiole, recale la lentille en trois demis-tours puis referme immédiatement. »\\n7. « Si la bobine demande une heure, reste ; une action trop rapide corrompt tout. »\\n8. « Trouve la marque de Sëthar sur l'étiquette ; elle confirme l'origine sans signature. »\\n9. « Prouve que l'envoi a été intercepté : photos, témoins, ou un lecteur certifié. »\\n10. « Si la Fraternité retrouve le lot avant quatorze jours, Sëthar est compromis. »\",\n      \"explanation\": \"Création de répliques courtes, techniques et jouables, respectant la longueur demandée.\"\n    },\n    {\n      \"type\": \"Style/Conventions\",\n      \"original\": \"Respecter les gloses (5-8 mots) pour les termes inventés\",\n      \"corrected\": \"Remarques de cohérence\\n- Termes conservés : fibremnésie, bobine, lecteur tactile certifié, implant de décodage, Fraternité, Sëthar (gloses préservées).\",\n      \"explanation\": \"Ajout d'une note de cohérence pour expliciter la préservation des néologismes et gloses.\"\n    },\n    {\n      \"type\": \"Ponctuation\",\n      \"original\": \"L'enregistrement exige 1 heure de manipulation et laisse trace visible.\",\n      \"corrected\": \"L'enregistrement exige une heure de manipulation continue et laisse une trace visible sur la tranche de la bobine (une strie argentée).\",\n      \"explanation\": \"Précision et ponctuation ajoutées pour améliorer la lisibilité.\"\n    }\n  ],\n  \"improvement_summary\": \"Texte clarifié et restructuré: définitions techniques précisées, enjeu de la dette développé, micro-gestes listés, élément de profondeur ajouté et dialogues conformes aux contraintes. Orthographe, grammaire et ponctuation corrigées sans altérer le sens ni les néologismes.\"\n}",
    "content": [
      {
        "type": "text",
        "text": "{\n  \"$defs\": {\n    \"_Corr\": {\n      \"properties\": {\n        \"type\": {\n          \"title\": \"Type\",\n          \"type\": \"string\"\n        },\n        \"original\": {\n          \"title\": \"Original\",\n          \"type\": \"string\"\n        },\n        \"corrected\": {\n          \"title\": \"Corrected\",\n          \"type\": \"string\"\n        },\n        \"explanation\": {\n          \"anyOf\": [\n            {\n              \"type\": \"string\"\n            },\n            {\n              \"type\": \"null\"\n            }\n          ],\n          \"default\": null,\n          \"title\": \"Explanation\"\n        }\n      },\n      \"required\": [\n        \"type\",\n        \"original\",\n        \"corrected\"\n      ],\n      \"title\": \"_Corr\",\n      \"type\": \"object\"\n    }\n  },\n  \"properties\": {\n    \"corrected_content\": {\n      \"anyOf\": [\n        {\n          \"type\": \"string\"\n        },\n        {\n          \"type\": \"null\"\n        }\n      ],\n      \"default\": null,\n      \"title\": \"Corrected Content\"\n    },\n    \"corrections\": {\n      \"items\": {\n        \"$ref\": \"#/$defs/_Corr\"\n      },\n      \"title\": \"Corrections\",\n      \"type\": \"array\"\n    },\n    \"improvement_summary\": {\n      \"default\": \"\",\n      \"title\": \"Improvement Summary\",\n      \"type\": \"string\"\n    }\n  },\n  \"title\": \"_CorrSchema\",\n  \"type\": \"object\",\n  \"corrected_content\": \"Fibremnésie\\nLes bobines de fibremnésie conservent les impressions pendant 30 cycles ; seul un lecteur tactile certifié peut décoder ces impressions sans corruption. L'enregistrement exige une heure de manipulation continue et laisse une trace visible sur la tranche de la bobine (une strie argentée). Toute tentative de décodage par un appareil non certifié altère irrémédiablement 40 % des données.\\nLe coût matériel d'un enregistrement est faible (fil fin, gel stabilisant), mais l'acte exige une compétence : niveau « opérateur de bobine » (formation de base) et un jet de précision (1 action prolongée). La suppression complète des impressions demande une station de neutralisation ou trente heures d'exposition à la lumière saline.\\nQui peut lire : seuls les lecteurs tactiles certifiés et certains archivistes initiés dotés d'un implant de décodage (glose : implant de décodage — module nerveux non invasif de lecture tissulaire) peuvent extraire la fibremnésie sans corruption. Durée de conservation : 30 cycles constatés en conditions normales ; variations possibles selon le gel stabilisant et l'humidité.\\n\\nDette d'Azrin — Enjeu précis\\nAzrin a expédié à une correspondante de la Fraternité trois mètres de tissu rare marqués d'un motif d'identité : bandes rouges cousues à la main et un sigle brodé en fil d'argent. Condition d'envoi : l'étiquette porte la marque de Sëthar et un comptage d'unités inscrit à l'encre thermosensible. Si la Fraternité retrouve l'envoi d'ici 14 jours, la piste mène directement à Sëthar : il sera suspecté, arrêté et interrogé. Conséquence secondaire : la perte de l'envoi compromet l'accès d'Azrin à la filière d'approvisionnement pour six mois.\\nRisque et réparation : Azrin doit prouver que l'envoi a été intercepté et falsifié pour éteindre les soupçons ; sinon, Sëthar risque la détention. La dette n'est donc pas seulement financière : elle est temporelle (14 jours) et informationnelle (preuve à fournir).\\n\\nSix micro-gestes de surface\\n- Passer la paume sur la bobine, pratiquement sans pression, pour lire la vibration résiduelle.\\n- Tapoter trois fois une corde en haut à gauche de la caisse pour activer son verrouillage muet.\\n- Nouer une étiquette avec un double nœud de signal (nœud visible uniquement au toucher).\\n- Frotter l'index contre l'intérieur d'une poche pour révéler une encre thermosensible.\\n- Retirer et recaler la lentille de lecture d'une fiole en trois demis-tours, timing précis.\\n- Souffler doucement sur une trace argentée ; la poussière révèle une séquence chiffrée.\\n\\nÉlément de profondeur indépendant du rôle\\nDans son enfance, Azrin regardait les vieux cartographes gratter des cartes anciennes, transformant les lignes effacées en récits. Il confia une fois : « Apprendre, c'est remettre la géographie en dette envers qui l'a oubliée. » Cette confession, entendue par un mentor, orienta son désir de connaissance : il collectionne désormais les impressions perdues comme on rançonne le souvenir. Ce n'est pas son métier qui le définit, mais cette petite cérémonie de restitution.\\n\\nDialogues (8-10 répliques techniques et jouables)\\n1. « Passe ta paume sur la bobine ; si la vibration clignote, elle est corrompue. »\\n2. « Tapote la corde trois fois, écoute le silence : il te dira si le verrou tient. »\\n3. « Noue l'étiquette deux fois ; un seul nœud peut être falsifié. »\\n4. « Montre-moi l'encre thermosensible avant d'envoyer ; elle change sous friction. »\\n5. « Rappelle-moi la séquence argentée : souffle et écoute la poussière chanter. »\\n6. « Ouvre la fiole, recale la lentille en trois demis-tours puis referme immédiatement. »\\n7. « Si la bobine demande une heure, reste ; une action trop rapide corrompt tout. »\\n8. « Trouve la marque de Sëthar sur l'étiquette ; elle confirme l'origine sans signature. »\\n9. « Prouve que l'envoi a été intercepté : photos, témoins, ou un lecteur certifié. »\\n10. « Si la Fraternité retrouve le lot avant quatorze jours, Sëthar est compromis. »\\n\\nRemarques de cohérence\\n- Termes conservés : fibremnésie, bobine, lecteur tactile certifié, implant de décodage, Fraternité, Sëthar (gloses préservées).\\n- Temps verbaux uniformisés au présent lorsque l'action est décrite ; le passé est ponctuel pour les faits passés.\\n- Ton cru mais informatif conservé : descriptions techniques et risques explicites sans esthétique de la violence.\",\n  \"corrections\": [\n    {\n      \"type\": \"Orthographe/Grammaire\",\n      \"original\": \"Les bobines conservent impressions 30 cycles ; seul un lecteur tactile certifié peut décoder sans corruption ; l'enregistrement exige 1 heure de manipulation et laisse trace visible.\",\n      \"corrected\": \"Les bobines de fibremnésie conservent les impressions pendant 30 cycles ; seul un lecteur tactile certifié peut décoder ces impressions sans corruption. L'enregistrement exige une heure de manipulation continue et laisse une trace visible sur la tranche de la bobine (une strie argentée).\",\n      \"explanation\": \"Correction des accords, ajout d'articles pour la clarté, remplacement du chiffre '1' par 'une' et scission en deux phrases pour la fluidité.\"\n    },\n    {\n      \"type\": \"Clarté\",\n      \"original\": \"Donner un enjeu précis pour la dette d'Azrin (ex : envoyée : 3 mètres de tissu rare marqués ; risque : si la Fraternité retrouve l'envoi dans 14 jours, Sëthar est suspecté).\",\n      \"corrected\": \"Azrin a expédié à une correspondante de la Fraternité trois mètres de tissu rare marqués d'un motif d'identité : bandes rouges cousues à la main et un sigle brodé en fil d'argent. Si la Fraternité retrouve l'envoi d'ici 14 jours, la piste mène directement à Sëthar : il sera suspecté, arrêté et interrogé.\",\n      \"explanation\": \"Reformulation pour préciser l'enjeu, garder les détails et expliciter les conséquences.\"\n    },\n    {\n      \"type\": \"Clarté/Style\",\n      \"original\": \"Ajouter 6 micro-gestes de surface (ex : passer la paume sur la bobine, tapoter trois fois une corde, nouer une étiquette avec un double nœud de signal).\",\n      \"corrected\": \"Six micro-gestes de surface\\n- Passer la paume sur la bobine, pratiquement sans pression, pour lire la vibration résiduelle.\\n- Tapoter trois fois une corde en haut à gauche de la caisse pour activer son verrouillage muet.\\n- Nouer une étiquette avec un double nœud de signal (nœud visible uniquement au toucher).\\n- Frotter l'index contre l'intérieur d'une poche pour révéler une encre thermosensible.\\n- Retirer et recaler la lentille de lecture d'une fiole en trois demis-tours, timing précis.\\n- Souffler doucement sur une trace argentée ; la poussière révèle une séquence chiffrée.\",\n      \"explanation\": \"Transformation en liste détaillée pour respecter l'instruction et accroître la jouabilité.\"\n    },\n    {\n      \"type\": \"Cohérence narrative\",\n      \"original\": \"Introduire un élément de profondeur indépendant du rôle (ex : une confession philosophique ou une vision d'enfance qui a orienté son désir de connaissance).\",\n      \"corrected\": \"Dans son enfance, Azrin regardait les vieux cartographes gratter des cartes anciennes, transformant les lignes effacées en récits. Il confia une fois : « Apprendre, c'est remettre la géographie en dette envers qui l'a oubliée. » Cette confession orienta son désir de connaissance : il collectionne désormais les impressions perdues comme on rançonne le souvenir.\",\n      \"explanation\": \"Ajout d'une ancre émotionnelle et d'une phrase révélatrice pour respecter la règle 'profond indépendamment du rôle'.\"\n    },\n    {\n      \"type\": \"Dialogues\",\n      \"original\": \"Corriger les dialogues et fournir 8-10 répliques de 10-20 mots, techniques et jouables.\",\n      \"corrected\": \"Dialogues (8-10 répliques techniques et jouables)\\n1. « Passe ta paume sur la bobine ; si la vibration clignote, elle est corrompue. »\\n2. « Tapote la corde trois fois, écoute le silence : il te dira si le verrou tient. »\\n3. « Noue l'étiquette deux fois ; un seul nœud peut être falsifié. »\\n4. « Montre-moi l'encre thermosensible avant d'envoyer ; elle change sous friction. »\\n5. « Rappelle-moi la séquence argentée : souffle et écoute la poussière chanter. »\\n6. « Ouvre la fiole, recale la lentille en trois demis-tours puis referme immédiatement. »\\n7. « Si la bobine demande une heure, reste ; une action trop rapide corrompt tout. »\\n8. « Trouve la marque de Sëthar sur l'étiquette ; elle confirme l'origine sans signature. »\\n9. « Prouve que l'envoi a été intercepté : photos, témoins, ou un lecteur certifié. »\\n10. « Si la Fraternité retrouve le lot avant quatorze jours, Sëthar est compromis. »\",\n      \"explanation\": \"Création de répliques courtes, techniques et jouables, respectant la longueur demandée.\"\n    },\n    {\n      \"type\": \"Style/Conventions\",\n      \"original\": \"Respecter les gloses (5-8 mots) pour les termes inventés\",\n      \"corrected\": \"Remarques de cohérence\\n- Termes conservés : fibremnésie, bobine, lecteur tactile certifié, implant de décodage, Fraternité, Sëthar (gloses préservées).\",\n      \"explanation\": \"Ajout d'une note de cohérence pour expliciter la préservation des néologismes et gloses.\"\n    },\n    {\n      \"type\": \"Ponctuation\",\n      \"original\": \"L'enregistrement exige 1 heure de manipulation et laisse trace visible.\",\n      \"corrected\": \"L'enregistrement exige une heure de manipulation continue et laisse une trace visible sur la tranche de la bobine (une strie argentée).\",\n      \"explanation\": \"Précision et ponctuation ajoutées pour améliorer la lisibilité.\"\n    }\n  ],\n  \"improvement_summary\": \"Texte clarifié et restructuré: définitions techniques précisées, enjeu de la dette développé, micro-gestes listés, élément de profondeur ajouté et dialogues conformes aux contraintes. Orthographe, grammaire et ponctuation corrigées sans altérer le sens ni les néologismes.\"\n}",
        "annotations": []
      }
    ],
    "response_metadata": {
      "id": "resp_048ee945cfb1cd7a0068f0ebef2bec81948914f1a2c0232c75",
      "created_at": 1760619503.0,
      "metadata": {},
      "model": "gpt-5-mini-2025-08-07",
      "object": "response",
      "service_tier": "default",
      "status": "completed",
      "model_name": "gpt-5-mini-2025-08-07"
    },
    "type": "AIMessage"
  }
}